autowt/__init__.py
autowt/cli.py
autowt/cli_config.py
autowt/config.py
autowt/console.py
autowt/global_config.py
autowt/hooks.py
autowt/models.py
autowt/prompts.py
autowt/commands/__init__.py
autowt/commands/checkout.py
autowt/commands/cleanup.py
autowt/commands/config.css
autowt/commands/config.py
autowt/commands/ls.py
autowt/services/__init__.py
autowt/services/git.py
autowt/services/github.py
autowt/services/state.py
autowt/services/terminal.py
autowt/services/version_check.py
autowt/tui/__init__.py
autowt/tui/cleanup.css
autowt/tui/cleanup.py
autowt/tui/switch.css
autowt/tui/switch.py
autowt/utils/__init__.py
autowt/utils/platform.py
autowt-0.5.7.dist-info/METADATA
autowt-0.5.7.dist-info/WHEEL
autowt-0.5.7.dist-info/entry_points.txt
autowt-0.5.7.dist-info/licenses/LICENSE
autowt-0.5.7.dist-info/RECORD
