Metadata-Version: 2.4
Name: autowt
Version: 0.5.7
Summary: Customizable git worktree manager
Author-email: Steve <steve@example.com>
License-Expression: MIT
License-File: LICENSE
Keywords: development,git,workflow,worktree
Classifier: Development Status :: 3 - Alpha
Classifier: Intended Audience :: Developers
Classifier: License :: OSI Approved :: MIT License
Classifier: Programming Language :: Python :: 3
Classifier: Programming Language :: Python :: 3.10
Classifier: Programming Language :: Python :: 3.11
Classifier: Programming Language :: Python :: 3.12
Classifier: Programming Language :: Python :: 3.13
Classifier: Topic :: Software Development :: Version Control
Classifier: Topic :: System :: Shells
Requires-Python: >=3.10
Requires-Dist: automate-terminal>=0.1.10
Requires-Dist: click-aliases>=1.0.0
Requires-Dist: click>=8.0.0
Requires-Dist: rich>=13.0.0
Requires-Dist: textual>=0.50.0
Requires-Dist: toml>=0.10.0
